moviesdk/__init__.py
moviesdk/movie_client.py
moviesdk/movie_config.py
moviesdk/schemas/__init__.py
moviesdk/schemas/schemas.py
moviesdk-0.0.2.dist-info/METADATA
moviesdk-0.0.2.dist-info/WHEEL
moviesdk-0.0.2.dist-info/top_level.txt
moviesdk-0.0.2.dist-info/RECORD
